topsis/__init__.py
topsis/algo.py
topsis/main.py
topsis_102217128-0.0.3.dist-info/LICENSE
topsis_102217128-0.0.3.dist-info/METADATA
topsis_102217128-0.0.3.dist-info/WHEEL
topsis_102217128-0.0.3.dist-info/top_level.txt
topsis_102217128-0.0.3.dist-info/RECORD
